python_runtime/__init__.py
python_runtime/middleware.py
python_runtime-24.3.27.dist-info/METADATA
python_runtime-24.3.27.dist-info/WHEEL
python_runtime-24.3.27.dist-info/top_level.txt
python_runtime-24.3.27.dist-info/RECORD
