Metadata-Version: 2.1
Name: python-runtime
Version: 24.3.27
Summary: A middleware package to check for service expiration.
Author: Louie X. Walker
Author-email: louiewalker.lw1@gmail.com
Requires-Dist: fastapi
Requires-Dist: uvicorn
